{
  "generated": "2026-07-22T08:25:27.356Z",
  "count": 5,
  "items": [
    {
      "title": "Intel攜手Fortinet開發Security Processor 6，推進資安專用ASIC晶片布局 ",
      "link": "https://www.ithome.com.tw/news/177514",
      "isoDate": "2026-07-22T12:07:57.000Z",
      "source": "iThome",
      "category": "科技"
    },
    {
      "title": "AWS計費系統使用錯誤單位價格資料，部分客戶收到數十億美元異常費用通知",
      "link": "https://www.ithome.com.tw/news/177510",
      "isoDate": "2026-07-22T12:07:46.000Z",
      "source": "iThome",
      "category": "科技"
    },
    {
      "title": "駭客利用多個SharePoint漏洞從事攻擊，部署Webshell並竊取IIS機器金鑰",
      "link": "https://www.ithome.com.tw/news/177512",
      "isoDate": "2026-07-22T12:07:26.000Z",
      "source": "iThome",
      "category": "科技"
    },
    {
      "title": "微軟偕Mistral進駐歐洲主權AI雲基礎架構市場",
      "link": "https://www.ithome.com.tw/news/177515",
      "isoDate": "2026-07-22T12:07:03.000Z",
      "source": "iThome",
      "category": "科技"
    },
    {
      "title": "重大SharePoint漏洞被用於竊取機器金鑰",
      "link": "https://www.ithome.com.tw/news/177511",
      "isoDate": "2026-07-22T12:07:03.000Z",
      "source": "iThome",
      "category": "科技"
    }
  ]
}