{
  "generated": "2026-07-08T19:22:32.395Z",
  "count": 5,
  "items": [
    {
      "title": "太空牛仔出任務，老舊衛星「雨燕天文台」將實施在軌延壽首例",
      "link": "https://technews.tw/2026/07/08/link-spacecraft-set-for-mission-to-boost-nasas-swift-observatory/",
      "isoDate": "2026-07-08T14:32:13.000Z",
      "source": "科技新報",
      "category": "科技"
    },
    {
      "title": "群聯 6 月營收年增逾 300% 創新高，潘健成指 NAND 需求仍高度成長",
      "link": "https://finance.technews.tw/2026/07/08/phisons-june-revenue-increased-by-over-300-year-on-year-setting-a-new-record/",
      "isoDate": "2026-07-08T12:20:01.000Z",
      "source": "科技新報",
      "category": "科技"
    },
    {
      "title": "維護公司信用及股東權益，威盛董事會決議第五次買回庫藏股",
      "link": "https://finance.technews.tw/2026/07/08/via-technologies-board-of-directors-resolved-to-repurchase-treasury-shares-for-the-fifth-time/",
      "isoDate": "2026-07-08T12:10:59.000Z",
      "source": "科技新報",
      "category": "科技"
    },
    {
      "title": "駭客團體UAT-7810打造新的惡意軟體架設ORB網路",
      "link": "https://www.ithome.com.tw/news/177172",
      "isoDate": "2026-07-08T12:07:59.000Z",
      "source": "iThome",
      "category": "科技"
    },
    {
      "title": "調查商業間諜軟體濫用，歐洲議會PEGA委員會成員反遭Pegasus入侵",
      "link": "https://www.ithome.com.tw/news/177169",
      "isoDate": "2026-07-08T12:07:32.000Z",
      "source": "iThome",
      "category": "科技"
    }
  ]
}